setup.py
tal_distributions/Binomialdistribution.py
tal_distributions/Gaussiandistribution.py
tal_distributions/Generaldistribution.py
tal_distributions/__init__.py
tal_distributions.egg-info/PKG-INFO
tal_distributions.egg-info/SOURCES.txt
tal_distributions.egg-info/dependency_links.txt
tal_distributions.egg-info/not-zip-safe
tal_distributions.egg-info/top_level.txt